[
    {
        "begin_at": "2020-05-01T13:00:00Z",
        "end_at": null,
        "id": 4012,
        "league": {
            "id": 4158,
            "image_url": "https://cdn.pandascore.co/images/league/image/4158/800px-Esl_logo.png",
            "modified_at": "2019-02-25T17:17:32Z",
            "name": "ESL",
            "slug": "cs-go-esl",
            "url": null
        },
        "league_id": 4158,
        "live_supported": false,
        "matches": [
            {
                "begin_at": "2020-05-01T13:00:00Z",
                "detailed_stats": true,
                "draw": false,
                "end_at": null,
                "forfeit": false,
                "game_advantage": null,
                "id": 559286,
                "live": {
                    "opens_at": null,
                    "supported": false,
                    "url": null
                },
                "live_embed_url": null,
                "live_url": null,
                "match_type": "best_of",
                "modified_at": "2020-04-17T20:49:39Z",
                "name": "Natus Vincere vs Espada",
                "number_of_games": 3,
                "original_scheduled_at": "2020-05-01T13:00:00Z",
                "rescheduled": false,
                "scheduled_at": "2020-05-01T13:00:00Z",
                "slug": "natus-vincere-vs-espada-2020-05-01",
                "status": "not_started",
                "tournament_id": 4012,
                "winner_id": null
            },
            {
                "begin_at": "2020-05-01T13:00:00Z",
                "detailed_stats": true,
                "draw": false,
                "end_at": null,
                "forfeit": false,
                "game_advantage": null,
                "id": 559287,
                "live": {
                    "opens_at": null,
                    "supported": false,
                    "url": null
                },
                "live_embed_url": null,
                "live_url": null,
                "match_type": "best_of",
                "modified_at": "2020-04-17T20:49:51Z",
                "name": "pro100 vs Virtus.pro",
                "number_of_games": 3,
                "original_scheduled_at": "2020-05-01T13:00:00Z",
                "rescheduled": false,
                "scheduled_at": "2020-05-01T13:00:00Z",
                "slug": "pro100-vs-virtus-pro-2020-05-01",
                "status": "not_started",
                "tournament_id": 4012,
                "winner_id": null
            },
            {
                "begin_at": "2020-05-01T13:00:00Z",
                "detailed_stats": true,
                "draw": false,
                "end_at": null,
                "forfeit": false,
                "game_advantage": null,
                "id": 559288,
                "live": {
                    "opens_at": null,
                    "supported": false,
                    "url": null
                },
                "live_embed_url": null,
                "live_url": null,
                "match_type": "best_of",
                "modified_at": "2020-04-17T20:50:01Z",
                "name": "Syman vs Hard Legion",
                "number_of_games": 3,
                "original_scheduled_at": "2020-05-01T13:00:00Z",
                "rescheduled": false,
                "scheduled_at": "2020-05-01T13:00:00Z",
                "slug": "syman-vs-hard-legion-2020-05-01",
                "status": "not_started",
                "tournament_id": 4012,
                "winner_id": null
            },
            {
                "begin_at": "2020-05-03T13:00:00Z",
                "detailed_stats": true,
                "draw": false,
                "end_at": null,
                "forfeit": false,
                "game_advantage": null,
                "id": 559292,
                "live": {
                    "opens_at": null,
                    "supported": false,
                    "url": null
                },
                "live_embed_url": null,
                "live_url": null,
                "match_type": "best_of",
                "modified_at": "2020-04-17T20:52:32Z",
                "name": "Virtus.pro vs Natus Vincere",
                "number_of_games": 3,
                "original_scheduled_at": "2020-05-03T13:00:00Z",
                "rescheduled": false,
                "scheduled_at": "2020-05-03T13:00:00Z",
                "slug": "virtus-pro-vs-natus-vincere-2020-05-03",
                "status": "not_started",
                "tournament_id": 4012,
                "winner_id": null
            },
            {
                "begin_at": "2020-05-03T13:00:00Z",
                "detailed_stats": true,
                "draw": false,
                "end_at": null,
                "forfeit": false,
                "game_advantage": null,
                "id": 559293,
                "live": {
                    "opens_at": null,
                    "supported": false,
                    "url": null
                },
                "live_embed_url": null,
                "live_url": null,
                "match_type": "best_of",
                "modified_at": "2020-04-17T20:52:42Z",
                "name": "pro100 vs Hard Legion",
                "number_of_games": 3,
                "original_scheduled_at": "2020-05-03T13:00:00Z",
                "rescheduled": false,
                "scheduled_at": "2020-05-03T13:00:00Z",
                "slug": "pro100-vs-hard-legion-2020-05-03",
                "status": "not_started",
                "tournament_id": 4012,
                "winner_id": null
            },
            {
                "begin_at": "2020-05-03T13:00:00Z",
                "detailed_stats": true,
                "draw": false,
                "end_at": null,
                "forfeit": false,
                "game_advantage": null,
                "id": 559294,
                "live": {
                    "opens_at": null,
                    "supported": false,
                    "url": null
                },
                "live_embed_url": null,
                "live_url": null,
                "match_type": "best_of",
                "modified_at": "2020-04-17T20:52:53Z",
                "name": "Espada vs Syman",
                "number_of_games": 3,
                "original_scheduled_at": "2020-05-03T13:00:00Z",
                "rescheduled": false,
                "scheduled_at": "2020-05-03T13:00:00Z",
                "slug": "espada-vs-syman-2020-05-03",
                "status": "not_started",
                "tournament_id": 4012,
                "winner_id": null
            },
            {
                "begin_at": "2020-05-06T13:00:00Z",
                "detailed_stats": true,
                "draw": false,
                "end_at": null,
                "forfeit": false,
                "game_advantage": null,
                "id": 559298,
                "live": {
                    "opens_at": null,
                    "supported": false,
                    "url": null
                },
                "live_embed_url": null,
                "live_url": null,
                "match_type": "best_of",
                "modified_at": "2020-04-17T20:58:19Z",
                "name": "Hard Legion vs Espada",
                "number_of_games": 3,
                "original_scheduled_at": "2020-05-06T13:00:00Z",
                "rescheduled": false,
                "scheduled_at": "2020-05-06T13:00:00Z",
                "slug": "hard-legion-vs-espada-2020-05-06",
                "status": "not_started",
                "tournament_id": 4012,
                "winner_id": null
            },
            {
                "begin_at": "2020-05-06T13:00:00Z",
                "detailed_stats": true,
                "draw": false,
                "end_at": null,
                "forfeit": false,
                "game_advantage": null,
                "id": 559299,
                "live": {
                    "opens_at": null,
                    "supported": false,
                    "url": null
                },
                "live_embed_url": null,
                "live_url": null,
                "match_type": "best_of",
                "modified_at": "2020-04-17T20:58:32Z",
                "name": "pro100 vs Natus Vincere",
                "number_of_games": 3,
                "original_scheduled_at": "2020-05-06T13:00:00Z",
                "rescheduled": false,
                "scheduled_at": "2020-05-06T13:00:00Z",
                "slug": "pro100-vs-natus-vincere-2020-05-06",
                "status": "not_started",
                "tournament_id": 4012,
                "winner_id": null
            },
            {
                "begin_at": "2020-05-06T13:00:00Z",
                "detailed_stats": true,
                "draw": false,
                "end_at": null,
                "forfeit": false,
                "game_advantage": null,
                "id": 559300,
                "live": {
                    "opens_at": null,
                    "supported": false,
                    "url": null
                },
                "live_embed_url": null,
                "live_url": null,
                "match_type": "best_of",
                "modified_at": "2020-04-17T20:58:42Z",
                "name": "Syman vs Virtus.pro",
                "number_of_games": 3,
                "original_scheduled_at": "2020-05-06T13:00:00Z",
                "rescheduled": false,
                "scheduled_at": "2020-05-06T13:00:00Z",
                "slug": "syman-vs-virtus-pro-2020-05-06",
                "status": "not_started",
                "tournament_id": 4012,
                "winner_id": null
            },
            {
                "begin_at": "2020-05-08T13:00:00Z",
                "detailed_stats": true,
                "draw": false,
                "end_at": null,
                "forfeit": false,
                "game_advantage": null,
                "id": 559304,
                "live": {
                    "opens_at": null,
                    "supported": false,
                    "url": null
                },
                "live_embed_url": null,
                "live_url": null,
                "match_type": "best_of",
                "modified_at": "2020-04-17T21:00:14Z",
                "name": "Virtus.pro vs Hard Legion",
                "number_of_games": 3,
                "original_scheduled_at": "2020-05-08T13:00:00Z",
                "rescheduled": false,
                "scheduled_at": "2020-05-08T13:00:00Z",
                "slug": "virtus-pro-vs-hard-legion-2020-05-08",
                "status": "not_started",
                "tournament_id": 4012,
                "winner_id": null
            },
            {
                "begin_at": "2020-05-08T13:00:00Z",
                "detailed_stats": true,
                "draw": false,
                "end_at": null,
                "forfeit": false,
                "game_advantage": null,
                "id": 559305,
                "live": {
                    "opens_at": null,
                    "supported": false,
                    "url": null
                },
                "live_embed_url": null,
                "live_url": null,
                "match_type": "best_of",
                "modified_at": "2020-04-17T21:00:26Z",
                "name": "pro100 vs Espada",
                "number_of_games": 3,
                "original_scheduled_at": "2020-05-08T13:00:00Z",
                "rescheduled": false,
                "scheduled_at": "2020-05-08T13:00:00Z",
                "slug": "pro100-vs-espada-2020-05-08",
                "status": "not_started",
                "tournament_id": 4012,
                "winner_id": null
            },
            {
                "begin_at": "2020-05-08T13:00:00Z",
                "detailed_stats": true,
                "draw": false,
                "end_at": null,
                "forfeit": false,
                "game_advantage": null,
                "id": 559306,
                "live": {
                    "opens_at": null,
                    "supported": false,
                    "url": null
                },
                "live_embed_url": null,
                "live_url": null,
                "match_type": "best_of",
                "modified_at": "2020-04-17T21:00:40Z",
                "name": "Natus Vincere vs Syman",
                "number_of_games": 3,
                "original_scheduled_at": "2020-05-08T13:00:00Z",
                "rescheduled": false,
                "scheduled_at": "2020-05-08T13:00:00Z",
                "slug": "natus-vincere-vs-syman-2020-05-08",
                "status": "not_started",
                "tournament_id": 4012,
                "winner_id": null
            },
            {
                "begin_at": "2020-05-10T13:00:00Z",
                "detailed_stats": true,
                "draw": false,
                "end_at": null,
                "forfeit": false,
                "game_advantage": null,
                "id": 559310,
                "live": {
                    "opens_at": null,
                    "supported": false,
                    "url": null
                },
                "live_embed_url": null,
                "live_url": null,
                "match_type": "best_of",
                "modified_at": "2020-04-17T21:02:58Z",
                "name": "Hard Legion vs Natus Vincere",
                "number_of_games": 3,
                "original_scheduled_at": "2020-05-10T13:00:00Z",
                "rescheduled": false,
                "scheduled_at": "2020-05-10T13:00:00Z",
                "slug": "hard-legion-vs-natus-vincere-2020-05-10",
                "status": "not_started",
                "tournament_id": 4012,
                "winner_id": null
            },
            {
                "begin_at": "2020-05-10T13:00:00Z",
                "detailed_stats": true,
                "draw": false,
                "end_at": null,
                "forfeit": false,
                "game_advantage": null,
                "id": 559311,
                "live": {
                    "opens_at": null,
                    "supported": false,
                    "url": null
                },
                "live_embed_url": null,
                "live_url": null,
                "match_type": "best_of",
                "modified_at": "2020-04-17T21:03:09Z",
                "name": "pro100 vs Syman",
                "number_of_games": 3,
                "original_scheduled_at": "2020-05-10T13:00:00Z",
                "rescheduled": false,
                "scheduled_at": "2020-05-10T13:00:00Z",
                "slug": "pro100-vs-syman-2020-05-10",
                "status": "not_started",
                "tournament_id": 4012,
                "winner_id": null
            },
            {
                "begin_at": "2020-05-10T13:00:00Z",
                "detailed_stats": true,
                "draw": false,
                "end_at": null,
                "forfeit": false,
                "game_advantage": null,
                "id": 559312,
                "live": {
                    "opens_at": null,
                    "supported": false,
                    "url": null
                },
                "live_embed_url": null,
                "live_url": null,
                "match_type": "best_of",
                "modified_at": "2020-04-17T21:03:19Z",
                "name": "Espada vs Virtus.pro",
                "number_of_games": 3,
                "original_scheduled_at": "2020-05-10T13:00:00Z",
                "rescheduled": false,
                "scheduled_at": "2020-05-10T13:00:00Z",
                "slug": "espada-vs-virtus-pro-2020-05-10",
                "status": "not_started",
                "tournament_id": 4012,
                "winner_id": null
            }
        ],
        "modified_at": "2020-04-17T20:10:35Z",
        "name": "Group b",
        "prizepool": null,
        "serie": {
            "begin_at": "2020-04-30T13:00:00Z",
            "description": null,
            "end_at": null,
            "full_name": "One: Road to Rio - CIS 2020",
            "id": 2631,
            "league_id": 4158,
            "modified_at": "2020-04-17T21:03:26Z",
            "name": "One: Road to Rio - CIS",
            "season": null,
            "slug": "cs-go-esl-one-road-to-rio-cis-2020",
            "winner_id": null,
            "winner_type": null,
            "year": 2020
        },
        "serie_id": 2631,
        "slug": "cs-go-esl-one-road-to-rio-cis-2020-group-b",
        "teams": [
            {
                "acronym": null,
                "id": 3216,
                "image_url": "https://cdn.pandascore.co/images/team/image/3216/NATUS_VINCERE.png",
                "location": "UA",
                "modified_at": "2020-04-22T12:37:44Z",
                "name": "Natus Vincere",
                "slug": "natus-vincere-cs-go"
            },
            {
                "acronym": null,
                "id": 3288,
                "image_url": "https://cdn.pandascore.co/images/team/image/3288/600px_virtus.pro_2019.png",
                "location": "RU",
                "modified_at": "2020-04-17T20:10:24Z",
                "name": "Virtus.pro",
                "slug": "virtus-pro-75b4744b-43d9-4ebd-a8dc-f1e0f9be69b3"
            },
            {
                "acronym": null,
                "id": 5907,
                "image_url": "https://cdn.pandascore.co/images/team/image/5907/PRO.png",
                "location": "UA",
                "modified_at": "2020-04-17T20:10:17Z",
                "name": "pro100",
                "slug": "pro100"
            },
            {
                "acronym": null,
                "id": 124524,
                "image_url": "https://cdn.pandascore.co/images/team/image/124524/syman.png",
                "location": "KZ",
                "modified_at": "2020-04-17T22:45:55Z",
                "name": "Syman",
                "slug": "syman-cs-go"
            },
            {
                "acronym": null,
                "id": 126231,
                "image_url": "https://cdn.pandascore.co/images/team/image/126231/espada-cs-go.png",
                "location": "RU",
                "modified_at": "2020-04-18T22:04:53Z",
                "name": "Espada",
                "slug": "espada-cs-go"
            },
            {
                "acronym": null,
                "id": 126363,
                "image_url": "https://cdn.pandascore.co/images/team/image/126363/600px_hard_legion_esports_new.png",
                "location": "RU",
                "modified_at": "2020-04-17T20:10:35Z",
                "name": "Hard Legion",
                "slug": "ex-dreameaters"
            }
        ],
        "videogame": {
            "id": 3,
            "name": "CS:GO",
            "slug": "cs-go"
        },
        "winner_id": null,
        "winner_type": null
    },
    {
        "begin_at": "2020-04-30T13:00:00Z",
        "end_at": null,
        "id": 4011,
        "league": {
            "id": 4158,
            "image_url": "https://cdn.pandascore.co/images/league/image/4158/800px-Esl_logo.png",
            "modified_at": "2019-02-25T17:17:32Z",
            "name": "ESL",
            "slug": "cs-go-esl",
            "url": null
        },
        "league_id": 4158,
        "live_supported": false,
        "matches": [
            {
                "begin_at": "2020-04-30T13:00:00Z",
                "detailed_stats": true,
                "draw": false,
                "end_at": null,
                "forfeit": false,
                "game_advantage": null,
                "id": 559283,
                "live": {
                    "opens_at": null,
                    "supported": false,
                    "url": null
                },
                "live_embed_url": null,
                "live_url": null,
                "match_type": "best_of",
                "modified_at": "2020-04-17T20:15:26Z",
                "name": "Gambit Youngsters vs Spirit",
                "number_of_games": 3,
                "original_scheduled_at": "2020-04-30T13:00:00Z",
                "rescheduled": false,
                "scheduled_at": "2020-04-30T13:00:00Z",
                "slug": "gambit-youngsters-vs-spirit-2020-04-30",
                "status": "not_started",
                "tournament_id": 4011,
                "winner_id": null
            },
            {
                "begin_at": "2020-04-30T13:00:00Z",
                "detailed_stats": true,
                "draw": false,
                "end_at": null,
                "forfeit": false,
                "game_advantage": null,
                "id": 559284,
                "live": {
                    "opens_at": null,
                    "supported": false,
                    "url": null
                },
                "live_embed_url": null,
                "live_url": null,
                "match_type": "best_of",
                "modified_at": "2020-04-17T20:48:20Z",
                "name": "forZe vs Nemiga",
                "number_of_games": 3,
                "original_scheduled_at": "2020-04-30T13:00:00Z",
                "rescheduled": false,
                "scheduled_at": "2020-04-30T13:00:00Z",
                "slug": "forze-vs-nemiga-2020-04-30",
                "status": "not_started",
                "tournament_id": 4011,
                "winner_id": null
            },
            {
                "begin_at": "2020-04-30T13:00:00Z",
                "detailed_stats": true,
                "draw": false,
                "end_at": null,
                "forfeit": false,
                "game_advantage": null,
                "id": 559285,
                "live": {
                    "opens_at": null,
                    "supported": false,
                    "url": null
                },
                "live_embed_url": null,
                "live_url": null,
                "match_type": "best_of",
                "modified_at": "2020-04-17T20:48:36Z",
                "name": "Unique vs Winstrike",
                "number_of_games": 3,
                "original_scheduled_at": "2020-04-30T13:00:00Z",
                "rescheduled": false,
                "scheduled_at": "2020-04-30T13:00:00Z",
                "slug": "unique-vs-winstrike-2020-04-30",
                "status": "not_started",
                "tournament_id": 4011,
                "winner_id": null
            },
            {
                "begin_at": "2020-05-02T13:00:00Z",
                "detailed_stats": true,
                "draw": false,
                "end_at": null,
                "forfeit": false,
                "game_advantage": null,
                "id": 559289,
                "live": {
                    "opens_at": null,
                    "supported": false,
                    "url": null
                },
                "live_embed_url": null,
                "live_url": null,
                "match_type": "best_of",
                "modified_at": "2020-04-17T20:50:37Z",
                "name": "forZe vs Spirit",
                "number_of_games": 3,
                "original_scheduled_at": "2020-05-02T13:00:00Z",
                "rescheduled": false,
                "scheduled_at": "2020-05-02T13:00:00Z",
                "slug": "forze-vs-spirit-2020-05-02",
                "status": "not_started",
                "tournament_id": 4011,
                "winner_id": null
            },
            {
                "begin_at": "2020-05-02T13:00:00Z",
                "detailed_stats": true,
                "draw": false,
                "end_at": null,
                "forfeit": false,
                "game_advantage": null,
                "id": 559290,
                "live": {
                    "opens_at": null,
                    "supported": false,
                    "url": null
                },
                "live_embed_url": null,
                "live_url": null,
                "match_type": "best_of",
                "modified_at": "2020-04-17T20:50:47Z",
                "name": "Nemiga vs Winstrike",
                "number_of_games": 3,
                "original_scheduled_at": "2020-05-02T13:00:00Z",
                "rescheduled": false,
                "scheduled_at": "2020-05-02T13:00:00Z",
                "slug": "nemiga-vs-winstrike-2020-05-02",
                "status": "not_started",
                "tournament_id": 4011,
                "winner_id": null
            },
            {
                "begin_at": "2020-05-02T13:00:00Z",
                "detailed_stats": true,
                "draw": false,
                "end_at": null,
                "forfeit": false,
                "game_advantage": null,
                "id": 559291,
                "live": {
                    "opens_at": null,
                    "supported": false,
                    "url": null
                },
                "live_embed_url": null,
                "live_url": null,
                "match_type": "best_of",
                "modified_at": "2020-04-17T20:50:57Z",
                "name": "Gambit Youngsters vs Unique",
                "number_of_games": 3,
                "original_scheduled_at": "2020-05-02T13:00:00Z",
                "rescheduled": false,
                "scheduled_at": "2020-05-02T13:00:00Z",
                "slug": "gambit-youngsters-vs-unique-2020-05-02",
                "status": "not_started",
                "tournament_id": 4011,
                "winner_id": null
            },
            {
                "begin_at": "2020-05-05T13:00:00Z",
                "detailed_stats": true,
                "draw": false,
                "end_at": null,
                "forfeit": false,
                "game_advantage": null,
                "id": 559295,
                "live": {
                    "opens_at": null,
                    "supported": false,
                    "url": null
                },
                "live_embed_url": null,
                "live_url": null,
                "match_type": "best_of",
                "modified_at": "2020-04-17T20:56:26Z",
                "name": "forZe vs Winstrike",
                "number_of_games": 3,
                "original_scheduled_at": "2020-05-05T13:00:00Z",
                "rescheduled": false,
                "scheduled_at": "2020-05-05T13:00:00Z",
                "slug": "forze-vs-winstrike-2020-05-05",
                "status": "not_started",
                "tournament_id": 4011,
                "winner_id": null
            },
            {
                "begin_at": "2020-05-05T13:00:00Z",
                "detailed_stats": true,
                "draw": false,
                "end_at": null,
                "forfeit": false,
                "game_advantage": null,
                "id": 559296,
                "live": {
                    "opens_at": null,
                    "supported": false,
                    "url": null
                },
                "live_embed_url": null,
                "live_url": null,
                "match_type": "best_of",
                "modified_at": "2020-04-17T20:56:35Z",
                "name": "Spirit vs Unique",
                "number_of_games": 3,
                "original_scheduled_at": "2020-05-05T13:00:00Z",
                "rescheduled": false,
                "scheduled_at": "2020-05-05T13:00:00Z",
                "slug": "spirit-vs-unique-2020-05-05",
                "status": "not_started",
                "tournament_id": 4011,
                "winner_id": null
            },
            {
                "begin_at": "2020-05-05T13:00:00Z",
                "detailed_stats": true,
                "draw": false,
                "end_at": null,
                "forfeit": false,
                "game_advantage": null,
                "id": 559297,
                "live": {
                    "opens_at": null,
                    "supported": false,
                    "url": null
                },
                "live_embed_url": null,
                "live_url": null,
                "match_type": "best_of",
                "modified_at": "2020-04-17T20:56:49Z",
                "name": "Nemiga vs Gambit Youngsters",
                "number_of_games": 3,
                "original_scheduled_at": "2020-05-05T13:00:00Z",
                "rescheduled": false,
                "scheduled_at": "2020-05-05T13:00:00Z",
                "slug": "nemiga-vs-gambit-youngsters-2020-05-05",
                "status": "not_started",
                "tournament_id": 4011,
                "winner_id": null
            },
            {
                "begin_at": "2020-05-07T13:00:00Z",
                "detailed_stats": true,
                "draw": false,
                "end_at": null,
                "forfeit": false,
                "game_advantage": null,
                "id": 559301,
                "live": {
                    "opens_at": null,
                    "supported": false,
                    "url": null
                },
                "live_embed_url": null,
                "live_url": null,
                "match_type": "best_of",
                "modified_at": "2020-04-17T20:58:55Z",
                "name": "Winstrike vs Gambit Youngsters",
                "number_of_games": 3,
                "original_scheduled_at": "2020-05-07T13:00:00Z",
                "rescheduled": false,
                "scheduled_at": "2020-05-07T13:00:00Z",
                "slug": "winstrike-vs-gambit-youngsters-2020-05-07",
                "status": "not_started",
                "tournament_id": 4011,
                "winner_id": null
            },
            {
                "begin_at": "2020-05-07T13:00:00Z",
                "detailed_stats": true,
                "draw": false,
                "end_at": null,
                "forfeit": false,
                "game_advantage": null,
                "id": 559302,
                "live": {
                    "opens_at": null,
                    "supported": false,
                    "url": null
                },
                "live_embed_url": null,
                "live_url": null,
                "match_type": "best_of",
                "modified_at": "2020-04-17T20:59:08Z",
                "name": "forZe vs Unique",
                "number_of_games": 3,
                "original_scheduled_at": "2020-05-07T13:00:00Z",
                "rescheduled": false,
                "scheduled_at": "2020-05-07T13:00:00Z",
                "slug": "forze-vs-unique-2020-05-07",
                "status": "not_started",
                "tournament_id": 4011,
                "winner_id": null
            },
            {
                "begin_at": "2020-05-07T13:00:00Z",
                "detailed_stats": true,
                "draw": false,
                "end_at": null,
                "forfeit": false,
                "game_advantage": null,
                "id": 559303,
                "live": {
                    "opens_at": null,
                    "supported": false,
                    "url": null
                },
                "live_embed_url": null,
                "live_url": null,
                "match_type": "best_of",
                "modified_at": "2020-04-17T20:59:16Z",
                "name": "Spirit vs Nemiga",
                "number_of_games": 3,
                "original_scheduled_at": "2020-05-07T13:00:00Z",
                "rescheduled": false,
                "scheduled_at": "2020-05-07T13:00:00Z",
                "slug": "spirit-vs-nemiga-2020-05-07",
                "status": "not_started",
                "tournament_id": 4011,
                "winner_id": null
            },
            {
                "begin_at": "2020-05-09T13:00:00Z",
                "detailed_stats": true,
                "draw": false,
                "end_at": null,
                "forfeit": false,
                "game_advantage": null,
                "id": 559307,
                "live": {
                    "opens_at": null,
                    "supported": false,
                    "url": null
                },
                "live_embed_url": null,
                "live_url": null,
                "match_type": "best_of",
                "modified_at": "2020-04-17T21:02:16Z",
                "name": "forZe vs Gambit Youngsters",
                "number_of_games": 3,
                "original_scheduled_at": "2020-05-09T13:00:00Z",
                "rescheduled": false,
                "scheduled_at": "2020-05-09T13:00:00Z",
                "slug": "forze-vs-gambit-youngsters-2020-05-09",
                "status": "not_started",
                "tournament_id": 4011,
                "winner_id": null
            },
            {
                "begin_at": "2020-05-09T13:00:00Z",
                "detailed_stats": true,
                "draw": false,
                "end_at": null,
                "forfeit": false,
                "game_advantage": null,
                "id": 559308,
                "live": {
                    "opens_at": null,
                    "supported": false,
                    "url": null
                },
                "live_embed_url": null,
                "live_url": null,
                "match_type": "best_of",
                "modified_at": "2020-04-17T21:02:33Z",
                "name": "Unique vs Nemiga",
                "number_of_games": 3,
                "original_scheduled_at": "2020-05-09T13:00:00Z",
                "rescheduled": false,
                "scheduled_at": "2020-05-09T13:00:00Z",
                "slug": "unique-vs-nemiga-2020-05-09",
                "status": "not_started",
                "tournament_id": 4011,
                "winner_id": null
            },
            {
                "begin_at": "2020-05-09T13:00:00Z",
                "detailed_stats": true,
                "draw": false,
                "end_at": null,
                "forfeit": false,
                "game_advantage": null,
                "id": 559309,
                "live": {
                    "opens_at": null,
                    "supported": false,
                    "url": null
                },
                "live_embed_url": null,
                "live_url": null,
                "match_type": "best_of",
                "modified_at": "2020-04-17T21:02:41Z",
                "name": "Winstrike vs Spirit",
                "number_of_games": 3,
                "original_scheduled_at": "2020-05-09T13:00:00Z",
                "rescheduled": false,
                "scheduled_at": "2020-05-09T13:00:00Z",
                "slug": "winstrike-vs-spirit-2020-05-09",
                "status": "not_started",
                "tournament_id": 4011,
                "winner_id": null
            }
        ],
        "modified_at": "2020-04-17T20:09:03Z",
        "name": "Group a",
        "prizepool": null,
        "serie": {
            "begin_at": "2020-04-30T13:00:00Z",
            "description": null,
            "end_at": null,
            "full_name": "One: Road to Rio - CIS 2020",
            "id": 2631,
            "league_id": 4158,
            "modified_at": "2020-04-17T21:03:26Z",
            "name": "One: Road to Rio - CIS",
            "season": null,
            "slug": "cs-go-esl-one-road-to-rio-cis-2020",
            "winner_id": null,
            "winner_type": null,
            "year": 2020
        },
        "serie_id": 2631,
        "slug": "cs-go-esl-one-road-to-rio-cis-2020-group-a",
        "teams": [
            {
                "acronym": null,
                "id": 3393,
                "image_url": "https://cdn.pandascore.co/images/team/image/3393/600px_winstrike_team_2019_logo.png",
                "location": "RU",
                "modified_at": "2020-04-17T20:09:03Z",
                "name": "Winstrike",
                "slug": "winstrike"
            },
            {
                "acronym": null,
                "id": 60201,
                "image_url": "https://cdn.pandascore.co/images/team/image/60201/FORZE.png",
                "location": "RU",
                "modified_at": "2020-04-17T20:07:42Z",
                "name": "forZe",
                "slug": "forze"
            },
            {
                "acronym": null,
                "id": 124522,
                "image_url": "https://cdn.pandascore.co/images/team/image/124522/NEMIGA.png",
                "location": "BY",
                "modified_at": "2020-04-17T20:07:53Z",
                "name": "Nemiga",
                "slug": "nemiga"
            },
            {
                "acronym": null,
                "id": 124523,
                "image_url": "https://cdn.pandascore.co/images/team/image/124523/spirit.png",
                "location": "RU",
                "modified_at": "2020-04-22T12:37:29Z",
                "name": "Spirit",
                "slug": "spirit"
            },
            {
                "acronym": null,
                "id": 126150,
                "image_url": "https://cdn.pandascore.co/images/team/image/126150/gambit-youngsters.png",
                "location": "RU",
                "modified_at": "2020-04-17T20:07:28Z",
                "name": "Gambit Youngsters",
                "slug": "gambit-youngsters"
            },
            {
                "acronym": null,
                "id": 126151,
                "image_url": "https://cdn.pandascore.co/images/team/image/126151/9287.png",
                "location": "RU",
                "modified_at": "2020-04-18T22:04:59Z",
                "name": "Unique",
                "slug": "unique"
            }
        ],
        "videogame": {
            "id": 3,
            "name": "CS:GO",
            "slug": "cs-go"
        },
        "winner_id": null,
        "winner_type": null
    }
]
